nbconvertjkl/__init__.py
nbconvertjkl/__main__.py
nbconvertjkl/cli.py
nbconvertjkl/config.py
nbconvertjkl/converter.py
nbconvertjkl/log.py
nbconvertjkl-0.0.4.dist-info/licenses/LICENSE
nbconvertjkl-0.0.4.dist-info/METADATA
nbconvertjkl-0.0.4.dist-info/WHEEL
nbconvertjkl-0.0.4.dist-info/entry_points.txt
nbconvertjkl-0.0.4.dist-info/top_level.txt
nbconvertjkl-0.0.4.dist-info/RECORD
