Metadata-Version: 2.4
Name: nbconvertjkl
Version: 0.0.4
Summary: Custom Jupyter notebook converter
Author: fuzzy-tribble
License: MIT
Project-URL: Homepage, https://github.com/fuzzy-tribble/nbconvertjkl
Requires-Python: <3.12,>=3.11
License-File: LICENSE
Requires-Dist: attrs==19.3.0
Requires-Dist: bleach==3.1.0
Requires-Dist: Click==7.0
Requires-Dist: decorator==4.4.1
Requires-Dist: defusedxml==0.6.0
Requires-Dist: entrypoints==0.3
Requires-Dist: importlib-metadata==1.4.0
Requires-Dist: ipython-genutils==0.2.0
Requires-Dist: Jinja2==2.10.3
Requires-Dist: jsonschema==3.2.0
Requires-Dist: jupyter-core==4.6.1
Requires-Dist: MarkupSafe==1.1.1
Requires-Dist: mistune==0.8.4
Requires-Dist: more-itertools==8.1.0
Requires-Dist: nbconvert==5.6.1
Requires-Dist: nbformat==5.0.4
Requires-Dist: pandocfilters==1.4.2
Requires-Dist: Pygments==2.5.2
Requires-Dist: pyrsistent==0.15.7
Requires-Dist: PyYAML==6.0.1
Requires-Dist: six==1.14.0
Requires-Dist: testpath==0.4.4
Requires-Dist: traitlets==4.3.3
Requires-Dist: webencodings==0.5.1
Requires-Dist: zipp==2.0.1
Provides-Extra: dev
Requires-Dist: build; extra == "dev"
Requires-Dist: twine; extra == "dev"
Requires-Dist: tqdm; extra == "dev"
Requires-Dist: requests; extra == "dev"
Dynamic: license-file
